readeck/__init__.py
readeck/client.py
readeck/exceptions.py
readeck/models.py
readeck-0.1.5.dist-info/METADATA
readeck-0.1.5.dist-info/WHEEL
readeck-0.1.5.dist-info/licenses/LICENSE
readeck-0.1.5.dist-info/RECORD
