Metadata-Version: 2.4
Name: readeck
Version: 0.1.5
Summary: Python client library for Readeck APIs
Project-URL: Homepage, https://github.com/yashvanzara/readeck-python
Project-URL: Documentation, https://github.com/yashvanzara/readeck-python#readme
Project-URL: Repository, https://github.com/yashvanzara/readeck-python
Project-URL: Issues, https://github.com/yashvanzara/readeck-python/issues
Project-URL: Changelog, https://github.com/yashvanzara/readeck-python/blob/main/CHANGELOG.md
Author-email: Yash Vanzara <yashvanzara@gmail.com>
License-Expression: MIT
License-File: LICENSE
Keywords: api,bookmark,client,readeck,reader
Classifier: Development Status :: 4 - Beta
Classifier: Intended Audience :: Developers
Classifier: License :: OSI Approved :: MIT License
Classifier: Operating System :: OS Independent
Classifier: Programming Language :: Python :: 3
Classifier: Programming Language :: Python :: 3.10
Classifier: Programming Language :: Python :: 3.11
Classifier: Programming Language :: Python :: 3.12
Classifier: Topic :: Internet :: WWW/HTTP
Classifier: Topic :: Software Development :: Libraries :: Python Modules
Requires-Python: >=3.10
Requires-Dist: httpx>=0.24.0
Requires-Dist: pydantic>=2.0.0
Requires-Dist: pyyaml>=6.0
